README
setup.cfg
setup.py
allegedb/__init__.py
allegedb/alchemy.py
allegedb/cache.py
allegedb/graph.py
allegedb/query.py
allegedb/sqlite.json
allegedb/window.py
allegedb/wrap.py
allegedb.egg-info/PKG-INFO
allegedb.egg-info/SOURCES.txt
allegedb.egg-info/dependency_links.txt
allegedb.egg-info/requires.txt
allegedb.egg-info/top_level.txt