Metadata-Version: 1.0
Name: allegedb
Version: 0.14.0
Summary: An object-relational mapper serving database-backed versions of the standard networkx graph classes.
Home-page: https://github.com/LogicalDash/LiSE
Author: Zachary Spector
Author-email: zacharyspector@gmail.com
License: AGPL3+
Keywords: orm graph networkx sql database
Platform: UNKNOWN
